README.md
setup.py
doe/__init__.py
doe/crd.py
doe/latin_square.py
doe/rcbd.py
doe.egg-info/PKG-INFO
doe.egg-info/SOURCES.txt
doe.egg-info/dependency_links.txt
doe.egg-info/requires.txt
doe.egg-info/top_level.txt