Metadata-Version: 2.1
Name: doe
Version: 0.1.3
Summary: A simple library for design of experiments and analysis in Python
Home-page: https://github.com/pawanaichra/doe
Author: Pawan Aichra
Author-email: aichrapawan@gmail.com
License: MIT
Keywords: DOE,design of experiments,experimental design,analysis of experiments,crd rcbd latin square
Platform: UNKNOWN
Classifier: Development Status :: 3 - Alpha
Classifier: License :: OSI Approved :: MIT License
Classifier: Programming Language :: Python :: 3.7
Classifier: Topic :: Scientific/Engineering :: Mathematics
Classifier: Intended Audience :: Education
Classifier: Intended Audience :: Science/Research
